{
    "date_time_utc": "2025-04-24T00:52:22.514831+00:00",
    "workflow_name": "AWS Lambda Evaluation",
    "execution_tag": "wetag_1745455389249",
    "workflow_start_time_ms": 1745455389249,
    "workflow_end_time_ms": 1745455942514,
    "workflow_runtime_data": {
        "input_files": [
            {
                "data": "ORTHOMCL1"
            },
            {
                "data": "ORTHOMCL256_2"
            },
            {
                "data": "ORTHOMCL320"
            },
            {
                "data": "ORTHOMCL371"
            },
            {
                "data": "ORTHOMCL510"
            },
            {
                "data": "ORTHOMCL617"
            },
            {
                "data": "ORTHOMCL652"
            },
            {
                "data": "ORTHOMCL721"
            },
            {
                "data": "ORTHOMCL744"
            },
            {
                "data": "ORTHOMCL746"
            },
            {
                "data": "ORTHOMCL763"
            },
            {
                "data": "ORTHOMCL830"
            },
            {
                "data": "ORTHOMCL854"
            },
            {
                "data": "ORTHOMCL875"
            },
            {
                "data": "ORTHOMCL884"
            },
            {
                "data": "ORTHOMCL885"
            },
            {
                "data": "ORTHOMCL938"
            },
            {
                "data": "ORTHOMCL964"
            },
            {
                "data": "ORTHOMCL965"
            },
            {
                "data": "ORTHOMCL974"
            },
            {
                "data": "ORTHOMCL1005"
            },
            {
                "data": "ORTHOMCL1021"
            },
            {
                "data": "ORTHOMCL1033"
            },
            {
                "data": "ORTHOMCL1034"
            },
            {
                "data": "ORTHOMCL1042"
            },
            {
                "data": "ORTHOMCL1087"
            },
            {
                "data": "ORTHOMCL1092"
            },
            {
                "data": "ORTHOMCL1125"
            },
            {
                "data": "ORTHOMCL1126"
            },
            {
                "data": "ORTHOMCL1136"
            },
            {
                "data": "ORTHOMCL1147"
            },
            {
                "data": "ORTHOMCL1166"
            },
            {
                "data": "ORTHOMCL1305"
            },
            {
                "data": "ORTHOMCL1311"
            },
            {
                "data": "ORTHOMCL1352"
            },
            {
                "data": "ORTHOMCL1363"
            },
            {
                "data": "ORTHOMCL1408"
            },
            {
                "data": "ORTHOMCL1410"
            },
            {
                "data": "ORTHOMCL1619"
            },
            {
                "data": "ORTHOMCL1833"
            },
            {
                "data": "ORTHOMCL1916"
            },
            {
                "data": "ORTHOMCL1940"
            },
            {
                "data": "ORTHOMCL1958"
            },
            {
                "data": "ORTHOMCL1984"
            },
            {
                "data": "ORTHOMCL2001"
            }
        ],
        "tree_files": [
            {
                "request_id": "08fc4da9-6bd7-405b-8162-f8824dca8975",
                "data": [
                    "tree_ORTHOMCL1.nexus"
                ]
            },
            {
                "request_id": "64f3338f-8199-40a3-a5ce-99be0b693543",
                "data": [
                    "tree_ORTHOMCL256_2.nexus"
                ]
            },
            {
                "request_id": "6959d44e-955e-4873-971d-fec5210582d9",
                "data": [
                    "tree_ORTHOMCL320.nexus"
                ]
            },
            {
                "request_id": "40391409-e044-4ba8-8394-95e07b75c518",
                "data": [
                    "tree_ORTHOMCL371.nexus"
                ]
            },
            {
                "request_id": "bf27f557-bbfa-47c1-91df-245fa1c56f5e",
                "data": [
                    "tree_ORTHOMCL510.nexus"
                ]
            },
            {
                "request_id": "97fd50af-aa99-4743-ba37-0f2e5ead7b06",
                "data": [
                    "tree_ORTHOMCL617.nexus"
                ]
            },
            {
                "request_id": "99eed610-f86b-4d34-b522-3574462042e9",
                "data": [
                    "tree_ORTHOMCL652.nexus"
                ]
            },
            {
                "request_id": "6fad865a-716c-4f01-8ab6-d1949c537ab4",
                "data": [
                    "tree_ORTHOMCL721.nexus"
                ]
            },
            {
                "request_id": "26804601-f287-4b5a-beff-5d942f68986a",
                "data": [
                    "tree_ORTHOMCL744.nexus"
                ]
            },
            {
                "request_id": "d698786f-ff9d-431f-a5eb-315902457442",
                "data": [
                    "tree_ORTHOMCL746.nexus"
                ]
            },
            {
                "request_id": "7b85215a-b9c4-4ad9-8bba-606ee276a53b",
                "data": [
                    "tree_ORTHOMCL763.nexus"
                ]
            },
            {
                "request_id": "0b83b3c9-7cbe-41ee-ad36-b3e209833b71",
                "data": [
                    "tree_ORTHOMCL830.nexus"
                ]
            },
            {
                "request_id": "ee23bea8-fd52-4676-8ee8-0bdf1a551c7e",
                "data": [
                    "tree_ORTHOMCL854.nexus"
                ]
            },
            {
                "request_id": "0dc77898-75b1-43a6-bb9c-cdecd314c795",
                "data": [
                    "tree_ORTHOMCL875.nexus"
                ]
            },
            {
                "request_id": "93e786db-ba2a-4ee6-bbe8-e356863798a9",
                "data": [
                    "tree_ORTHOMCL884.nexus"
                ]
            },
            {
                "request_id": "a22f591f-14a1-4919-99fa-5652645cf0d8",
                "data": [
                    "tree_ORTHOMCL885.nexus"
                ]
            },
            {
                "request_id": "a5b1a1f0-bb43-4e52-8eb3-8687878db44e",
                "data": [
                    "tree_ORTHOMCL938.nexus"
                ]
            },
            {
                "request_id": "414a8a84-697c-4dd9-bd68-378488535bf1",
                "data": [
                    "tree_ORTHOMCL964.nexus"
                ]
            },
            {
                "request_id": "9c6fd1f8-6264-4bd7-95e6-ec1fca9e68ce",
                "data": [
                    "tree_ORTHOMCL965.nexus"
                ]
            },
            {
                "request_id": "77123a04-c48d-42d0-aac5-2ead33854692",
                "data": [
                    "tree_ORTHOMCL974.nexus"
                ]
            },
            {
                "request_id": "97e4212c-13a7-4657-9381-c31870ac5871",
                "data": [
                    "tree_ORTHOMCL1005.nexus"
                ]
            },
            {
                "request_id": "f2c2ae90-fcef-4612-b318-82b160020ac5",
                "data": [
                    "tree_ORTHOMCL1021.nexus"
                ]
            },
            {
                "request_id": "47565368-36b2-4ba3-8b8c-efba590cbd3c",
                "data": [
                    "tree_ORTHOMCL1033.nexus"
                ]
            },
            {
                "request_id": "952e2f42-918d-4503-8417-65a12eb14890",
                "data": [
                    "tree_ORTHOMCL1034.nexus"
                ]
            },
            {
                "request_id": "64bf0a4b-0bab-4f37-bd2f-df23ba12e7c7",
                "data": [
                    "tree_ORTHOMCL1042.nexus"
                ]
            },
            {
                "request_id": "44615378-6d69-447f-aab1-62e5ebc84e05",
                "data": [
                    "tree_ORTHOMCL1087.nexus"
                ]
            },
            {
                "request_id": "3008952d-b53d-4aaf-81fc-e3669f21424a",
                "data": [
                    "tree_ORTHOMCL1092.nexus"
                ]
            },
            {
                "request_id": "30fd4d19-8e5e-4a48-ab10-a7a3b08a88e9",
                "data": [
                    "tree_ORTHOMCL1125.nexus"
                ]
            },
            {
                "request_id": "51780a65-67ec-4d97-bb7e-408117a5bc3b",
                "data": [
                    "tree_ORTHOMCL1126.nexus"
                ]
            },
            {
                "request_id": "6dc8af92-a8ca-4cb1-9da6-998631f75aa0",
                "data": [
                    "tree_ORTHOMCL1136.nexus"
                ]
            },
            {
                "request_id": "c5cf35e8-2e54-4a2d-b9a2-d12670d144ca",
                "data": [
                    "tree_ORTHOMCL1147.nexus"
                ]
            },
            {
                "request_id": "14d8b179-ae1f-49dc-bbb6-fe0d34a1756e",
                "data": [
                    "tree_ORTHOMCL1166.nexus"
                ]
            },
            {
                "request_id": "168f89dc-c52c-495e-b474-2b82d16cd39a",
                "data": [
                    "tree_ORTHOMCL1305.nexus"
                ]
            },
            {
                "request_id": "b40b68fb-7313-4958-9715-aa9cff5f161d",
                "data": [
                    "tree_ORTHOMCL1311.nexus"
                ]
            },
            {
                "request_id": "ee6860c3-fc9d-4581-baf2-9f1c7f47f36c",
                "data": [
                    "tree_ORTHOMCL1352.nexus"
                ]
            },
            {
                "request_id": "6421c280-c792-4365-817a-de41bbe78321",
                "data": [
                    "tree_ORTHOMCL1363.nexus"
                ]
            },
            {
                "request_id": "69ec90f8-18af-4695-bd72-7063bd913e9a",
                "data": [
                    "tree_ORTHOMCL1408.nexus"
                ]
            },
            {
                "request_id": "a5d2fcc1-7d18-4cc0-b643-7a809e5880e3",
                "data": [
                    "tree_ORTHOMCL1410.nexus"
                ]
            },
            {
                "request_id": "4cddd12d-d48e-43a6-8fe6-7bf3e9f7c56e",
                "data": [
                    "tree_ORTHOMCL1619.nexus"
                ]
            },
            {
                "request_id": "580be588-c75f-4da3-aa33-8323014acc39",
                "data": [
                    "tree_ORTHOMCL1833.nexus"
                ]
            },
            {
                "request_id": "3079b5cf-b701-4db2-b857-9e0d5b496aec",
                "data": [
                    "tree_ORTHOMCL1916.nexus"
                ]
            },
            {
                "request_id": "fab5c55f-1ba2-4b78-ada8-82413739e9e8",
                "data": [
                    "tree_ORTHOMCL1940.nexus"
                ]
            },
            {
                "request_id": "580640e1-e22d-4317-b3eb-ad98580814c3",
                "data": [
                    "tree_ORTHOMCL1958.nexus"
                ]
            },
            {
                "request_id": "16e4d9ee-d90b-48e9-98ac-f463e56f0ffd",
                "data": [
                    "tree_ORTHOMCL1984.nexus"
                ]
            },
            {
                "request_id": "df6ee1c6-37fd-4621-a4e7-e9dec3a5580e",
                "data": [
                    "tree_ORTHOMCL2001.nexus"
                ]
            }
        ],
        "subtree_files": [
            {
                "request_id": "0e7aa7fc-9288-4073-8fcf-92eb102e997c",
                "data": [
                    "tree_ORTHOMCL1_Inner1.nexus",
                    "tree_ORTHOMCL1_Inner2.nexus",
                    "tree_ORTHOMCL1_Inner3.nexus"
                ]
            },
            {
                "request_id": "340d180d-3a77-4e6e-8af9-057ae9f24a66",
                "data": [
                    "tree_ORTHOMCL256_2_Inner1.nexus",
                    "tree_ORTHOMCL256_2_Inner2.nexus",
                    "tree_ORTHOMCL256_2_Inner3.nexus",
                    "tree_ORTHOMCL256_2_Inner4.nexus",
                    "tree_ORTHOMCL256_2_Inner5.nexus",
                    "tree_ORTHOMCL256_2_Inner6.nexus",
                    "tree_ORTHOMCL256_2_Inner7.nexus",
                    "tree_ORTHOMCL256_2_Inner8.nexus"
                ]
            },
            {
                "request_id": "7b8f38d2-dab0-4ead-bc17-80648f515af7",
                "data": [
                    "tree_ORTHOMCL320_Inner1.nexus",
                    "tree_ORTHOMCL320_Inner2.nexus",
                    "tree_ORTHOMCL320_Inner3.nexus",
                    "tree_ORTHOMCL320_Inner4.nexus",
                    "tree_ORTHOMCL320_Inner5.nexus",
                    "tree_ORTHOMCL320_Inner6.nexus",
                    "tree_ORTHOMCL320_Inner7.nexus"
                ]
            },
            {
                "request_id": "14112750-00df-49bd-88cc-6d6b73d54a53",
                "data": [
                    "tree_ORTHOMCL371_Inner1.nexus",
                    "tree_ORTHOMCL371_Inner2.nexus",
                    "tree_ORTHOMCL371_Inner3.nexus",
                    "tree_ORTHOMCL371_Inner4.nexus",
                    "tree_ORTHOMCL371_Inner5.nexus",
                    "tree_ORTHOMCL371_Inner6.nexus"
                ]
            },
            {
                "request_id": "eebf2d12-1d95-4f46-b66c-abfc3ac2f6fc",
                "data": [
                    "tree_ORTHOMCL510_Inner1.nexus",
                    "tree_ORTHOMCL510_Inner2.nexus",
                    "tree_ORTHOMCL510_Inner3.nexus",
                    "tree_ORTHOMCL510_Inner4.nexus",
                    "tree_ORTHOMCL510_Inner5.nexus"
                ]
            },
            {
                "request_id": "f5199038-7b4d-4da0-b5b7-dbd0ab0da8f5",
                "data": [
                    "tree_ORTHOMCL617_Inner1.nexus",
                    "tree_ORTHOMCL617_Inner2.nexus",
                    "tree_ORTHOMCL617_Inner3.nexus",
                    "tree_ORTHOMCL617_Inner4.nexus",
                    "tree_ORTHOMCL617_Inner5.nexus"
                ]
            },
            {
                "request_id": "d84cc4ed-759a-4f46-9784-dd120b9fb53b",
                "data": [
                    "tree_ORTHOMCL652_Inner1.nexus",
                    "tree_ORTHOMCL652_Inner2.nexus",
                    "tree_ORTHOMCL652_Inner3.nexus",
                    "tree_ORTHOMCL652_Inner4.nexus",
                    "tree_ORTHOMCL652_Inner5.nexus"
                ]
            },
            {
                "request_id": "e006114e-a608-472d-a727-862bc2058a97",
                "data": [
                    "tree_ORTHOMCL721_Inner1.nexus",
                    "tree_ORTHOMCL721_Inner2.nexus",
                    "tree_ORTHOMCL721_Inner3.nexus",
                    "tree_ORTHOMCL721_Inner4.nexus"
                ]
            },
            {
                "request_id": "411cb172-ce23-4ab8-9d4b-c5603de736b9",
                "data": [
                    "tree_ORTHOMCL744_Inner1.nexus",
                    "tree_ORTHOMCL744_Inner2.nexus",
                    "tree_ORTHOMCL744_Inner3.nexus",
                    "tree_ORTHOMCL744_Inner4.nexus"
                ]
            },
            {
                "request_id": "35fc821e-65b5-43ab-a85b-ce07d7d5cc0f",
                "data": [
                    "tree_ORTHOMCL746_Inner1.nexus",
                    "tree_ORTHOMCL746_Inner2.nexus",
                    "tree_ORTHOMCL746_Inner3.nexus",
                    "tree_ORTHOMCL746_Inner4.nexus"
                ]
            },
            {
                "request_id": "fd1c8f38-a7c9-43ce-b229-a09dbdc080cc",
                "data": [
                    "tree_ORTHOMCL763_Inner1.nexus",
                    "tree_ORTHOMCL763_Inner2.nexus",
                    "tree_ORTHOMCL763_Inner3.nexus",
                    "tree_ORTHOMCL763_Inner4.nexus"
                ]
            },
            {
                "request_id": "809cebf2-c8f5-4161-87d2-a8b2a2824325",
                "data": [
                    "tree_ORTHOMCL830_Inner1.nexus",
                    "tree_ORTHOMCL830_Inner2.nexus",
                    "tree_ORTHOMCL830_Inner3.nexus",
                    "tree_ORTHOMCL830_Inner4.nexus"
                ]
            },
            {
                "request_id": "e19a85ab-83a8-4ba8-bd61-67a2d9949b54",
                "data": [
                    "tree_ORTHOMCL854_Inner1.nexus",
                    "tree_ORTHOMCL854_Inner2.nexus",
                    "tree_ORTHOMCL854_Inner3.nexus",
                    "tree_ORTHOMCL854_Inner4.nexus"
                ]
            },
            {
                "request_id": "f9c0cfdd-e9fd-48a3-b00e-c3eb14928fb3",
                "data": [
                    "tree_ORTHOMCL875_Inner1.nexus",
                    "tree_ORTHOMCL875_Inner2.nexus",
                    "tree_ORTHOMCL875_Inner3.nexus",
                    "tree_ORTHOMCL875_Inner4.nexus"
                ]
            },
            {
                "request_id": "04aeb07c-8a9e-4809-8b0f-e96827e35537",
                "data": [
                    "tree_ORTHOMCL884_Inner1.nexus",
                    "tree_ORTHOMCL884_Inner2.nexus",
                    "tree_ORTHOMCL884_Inner3.nexus",
                    "tree_ORTHOMCL884_Inner4.nexus"
                ]
            },
            {
                "request_id": "75138f8b-1d07-4d99-9fe2-2726c8bba2f1",
                "data": [
                    "tree_ORTHOMCL885_Inner1.nexus",
                    "tree_ORTHOMCL885_Inner2.nexus",
                    "tree_ORTHOMCL885_Inner3.nexus",
                    "tree_ORTHOMCL885_Inner4.nexus"
                ]
            },
            {
                "request_id": "364b3f25-d95e-4acb-8fbb-bffb508722de",
                "data": [
                    "tree_ORTHOMCL938_Inner1.nexus",
                    "tree_ORTHOMCL938_Inner2.nexus",
                    "tree_ORTHOMCL938_Inner3.nexus",
                    "tree_ORTHOMCL938_Inner4.nexus"
                ]
            },
            {
                "request_id": "5e16ddc9-a8da-4f2e-9f53-545df65d9459",
                "data": [
                    "tree_ORTHOMCL964_Inner1.nexus",
                    "tree_ORTHOMCL964_Inner2.nexus",
                    "tree_ORTHOMCL964_Inner3.nexus",
                    "tree_ORTHOMCL964_Inner4.nexus"
                ]
            },
            {
                "request_id": "9e7b24e4-50b6-4d7c-9c32-0117b341d080",
                "data": [
                    "tree_ORTHOMCL965_Inner1.nexus",
                    "tree_ORTHOMCL965_Inner2.nexus",
                    "tree_ORTHOMCL965_Inner3.nexus",
                    "tree_ORTHOMCL965_Inner4.nexus"
                ]
            },
            {
                "request_id": "be69390c-1762-4811-b332-2992aa90af9f",
                "data": [
                    "tree_ORTHOMCL974_Inner1.nexus",
                    "tree_ORTHOMCL974_Inner2.nexus",
                    "tree_ORTHOMCL974_Inner3.nexus",
                    "tree_ORTHOMCL974_Inner4.nexus"
                ]
            },
            {
                "request_id": "2ff3b699-be02-42ee-bcd8-7141342c1096",
                "data": [
                    "tree_ORTHOMCL1005_Inner1.nexus",
                    "tree_ORTHOMCL1005_Inner2.nexus",
                    "tree_ORTHOMCL1005_Inner3.nexus",
                    "tree_ORTHOMCL1005_Inner4.nexus"
                ]
            },
            {
                "request_id": "960df21c-998d-4534-8df1-83250d32ee6d",
                "data": [
                    "tree_ORTHOMCL1021_Inner1.nexus",
                    "tree_ORTHOMCL1021_Inner2.nexus",
                    "tree_ORTHOMCL1021_Inner3.nexus",
                    "tree_ORTHOMCL1021_Inner4.nexus"
                ]
            },
            {
                "request_id": "74652ed1-ee86-4086-9c3c-a1b36bbbb3ef",
                "data": [
                    "tree_ORTHOMCL1033_Inner1.nexus",
                    "tree_ORTHOMCL1033_Inner2.nexus",
                    "tree_ORTHOMCL1033_Inner3.nexus",
                    "tree_ORTHOMCL1033_Inner4.nexus"
                ]
            },
            {
                "request_id": "4829f72d-2a1a-4f53-988b-75f794702eb9",
                "data": [
                    "tree_ORTHOMCL1034_Inner1.nexus",
                    "tree_ORTHOMCL1034_Inner2.nexus",
                    "tree_ORTHOMCL1034_Inner3.nexus",
                    "tree_ORTHOMCL1034_Inner4.nexus"
                ]
            },
            {
                "request_id": "cf0e8fd8-22be-4433-b4bf-b768379e688e",
                "data": [
                    "tree_ORTHOMCL1042_Inner1.nexus",
                    "tree_ORTHOMCL1042_Inner2.nexus",
                    "tree_ORTHOMCL1042_Inner3.nexus",
                    "tree_ORTHOMCL1042_Inner4.nexus"
                ]
            },
            {
                "request_id": "5dc409bb-d7f3-4e16-badf-eb6ea18db0fe",
                "data": [
                    "tree_ORTHOMCL1087_Inner1.nexus",
                    "tree_ORTHOMCL1087_Inner2.nexus",
                    "tree_ORTHOMCL1087_Inner3.nexus",
                    "tree_ORTHOMCL1087_Inner4.nexus"
                ]
            },
            {
                "request_id": "4dc84d1d-d944-4238-a2f7-0329a3325e07",
                "data": [
                    "tree_ORTHOMCL1092_Inner1.nexus",
                    "tree_ORTHOMCL1092_Inner2.nexus",
                    "tree_ORTHOMCL1092_Inner3.nexus",
                    "tree_ORTHOMCL1092_Inner4.nexus"
                ]
            },
            {
                "request_id": "dd11ee7f-f87f-4974-bafe-17d9e2e863aa",
                "data": [
                    "tree_ORTHOMCL1125_Inner1.nexus",
                    "tree_ORTHOMCL1125_Inner2.nexus",
                    "tree_ORTHOMCL1125_Inner3.nexus",
                    "tree_ORTHOMCL1125_Inner4.nexus"
                ]
            },
            {
                "request_id": "34a917c6-54d3-44a1-bb3e-fece7d70ee1d",
                "data": [
                    "tree_ORTHOMCL1126_Inner1.nexus",
                    "tree_ORTHOMCL1126_Inner2.nexus",
                    "tree_ORTHOMCL1126_Inner3.nexus",
                    "tree_ORTHOMCL1126_Inner4.nexus"
                ]
            },
            {
                "request_id": "d535ebd0-1d36-44d4-8737-4bffc4404c7e",
                "data": [
                    "tree_ORTHOMCL1136_Inner1.nexus",
                    "tree_ORTHOMCL1136_Inner2.nexus",
                    "tree_ORTHOMCL1136_Inner3.nexus",
                    "tree_ORTHOMCL1136_Inner4.nexus"
                ]
            },
            {
                "request_id": "163d348d-6a33-4c0a-a843-1f9425e9afb4",
                "data": [
                    "tree_ORTHOMCL1147_Inner1.nexus",
                    "tree_ORTHOMCL1147_Inner2.nexus",
                    "tree_ORTHOMCL1147_Inner3.nexus",
                    "tree_ORTHOMCL1147_Inner4.nexus"
                ]
            },
            {
                "request_id": "77a1eded-1f76-4f5c-b88c-60c81bb3212f",
                "data": [
                    "tree_ORTHOMCL1166_Inner1.nexus",
                    "tree_ORTHOMCL1166_Inner2.nexus",
                    "tree_ORTHOMCL1166_Inner3.nexus",
                    "tree_ORTHOMCL1166_Inner4.nexus"
                ]
            },
            {
                "request_id": "14edd325-e540-4435-90a2-885e5dbd6b57",
                "data": [
                    "tree_ORTHOMCL1305_Inner1.nexus",
                    "tree_ORTHOMCL1305_Inner2.nexus",
                    "tree_ORTHOMCL1305_Inner3.nexus"
                ]
            },
            {
                "request_id": "c957b042-12c7-49d7-a13d-560384ced523",
                "data": [
                    "tree_ORTHOMCL1311_Inner1.nexus",
                    "tree_ORTHOMCL1311_Inner2.nexus",
                    "tree_ORTHOMCL1311_Inner3.nexus"
                ]
            },
            {
                "request_id": "6541e812-824c-458f-bb67-c1132e9579a7",
                "data": [
                    "tree_ORTHOMCL1352_Inner1.nexus",
                    "tree_ORTHOMCL1352_Inner2.nexus",
                    "tree_ORTHOMCL1352_Inner3.nexus"
                ]
            },
            {
                "request_id": "82f3bc9a-d264-47ab-8928-52658a3bee68",
                "data": [
                    "tree_ORTHOMCL1363_Inner1.nexus",
                    "tree_ORTHOMCL1363_Inner2.nexus",
                    "tree_ORTHOMCL1363_Inner3.nexus"
                ]
            },
            {
                "request_id": "41c2003d-6c0f-41e2-b759-8cd241c32134",
                "data": [
                    "tree_ORTHOMCL1408_Inner1.nexus",
                    "tree_ORTHOMCL1408_Inner2.nexus",
                    "tree_ORTHOMCL1408_Inner3.nexus"
                ]
            },
            {
                "request_id": "9e3866f8-64f5-422e-86fa-4d110e382d5c",
                "data": [
                    "tree_ORTHOMCL1410_Inner1.nexus",
                    "tree_ORTHOMCL1410_Inner2.nexus",
                    "tree_ORTHOMCL1410_Inner3.nexus"
                ]
            },
            {
                "request_id": "5ea384c1-8c98-4b51-abe0-001a09c08d1f",
                "data": [
                    "tree_ORTHOMCL1619_Inner1.nexus",
                    "tree_ORTHOMCL1619_Inner2.nexus",
                    "tree_ORTHOMCL1619_Inner3.nexus"
                ]
            },
            {
                "request_id": "4fdcdd90-fc60-4adf-94ff-4b6f53e4591c",
                "data": [
                    "tree_ORTHOMCL1833_Inner1.nexus",
                    "tree_ORTHOMCL1833_Inner2.nexus",
                    "tree_ORTHOMCL1833_Inner3.nexus"
                ]
            },
            {
                "request_id": "0ddb0248-0434-42d0-b90c-04d79699c407",
                "data": [
                    "tree_ORTHOMCL1916_Inner1.nexus",
                    "tree_ORTHOMCL1916_Inner2.nexus",
                    "tree_ORTHOMCL1916_Inner3.nexus"
                ]
            },
            {
                "request_id": "e40115cc-dbdd-45c2-b07a-7c4a23825a9b",
                "data": [
                    "tree_ORTHOMCL1940_Inner1.nexus",
                    "tree_ORTHOMCL1940_Inner2.nexus",
                    "tree_ORTHOMCL1940_Inner3.nexus"
                ]
            },
            {
                "request_id": "cd4815c1-a5d9-4f40-9921-fe20797106b3",
                "data": [
                    "tree_ORTHOMCL1958_Inner1.nexus",
                    "tree_ORTHOMCL1958_Inner2.nexus",
                    "tree_ORTHOMCL1958_Inner3.nexus"
                ]
            },
            {
                "request_id": "36f029c6-f5fb-4ce5-a4ef-706f7eddf41a",
                "data": [
                    "tree_ORTHOMCL1984_Inner1.nexus",
                    "tree_ORTHOMCL1984_Inner2.nexus",
                    "tree_ORTHOMCL1984_Inner3.nexus"
                ]
            },
            {
                "request_id": "f671511b-b890-4c53-a28e-397760c79f75",
                "data": [
                    "tree_ORTHOMCL2001_Inner1.nexus",
                    "tree_ORTHOMCL2001_Inner2.nexus",
                    "tree_ORTHOMCL2001_Inner3.nexus"
                ]
            }
        ],
        "intermediate_mafdb_files": [
            {
                "request_id": "7843bfe1-2c5c-4baa-9631-754037b52035",
                "data": "mafdb_6f7a2b1116e6a791f68a03367473294792b679a6357b6789f3f993b1f83e2e80.json"
            },
            {
                "request_id": "1f7e3a90-2413-4c22-a375-e108068edb60",
                "data": "mafdb_5b18ebb61af0df9768d3f0de071bdfce6b107b0fc539962510ac2b333d1ae1e2.json"
            },
            {
                "request_id": "cbd5ca5e-ae7c-452b-b876-8613d97ca8e0",
                "data": "mafdb_bd5d862db8f1d6b261aaeb3b8ecb83d67004ffb7524cb75c5f1f8454224f7c91.json"
            },
            {
                "request_id": "a783aaf0-e988-485b-842f-1944e833b054",
                "data": "mafdb_7511017a4e93687a5be47b55aa4c08eff48c283a8153f5e070747057ad693f80.json"
            },
            {
                "request_id": "1cf54e2f-b453-4ac6-a66b-f6cecab1d86d",
                "data": "mafdb_783d326a98c97c227099cd46e1eb2739e8954c844e628390759f21e7b4e19db0.json"
            },
            {
                "request_id": "8fca8998-86c5-4db0-bbd7-4652beaf3ee2",
                "data": "mafdb_f6c9786df6a492206e55eb3d3911d34dbd753bfef23be22d8635d72135a7fbc7.json"
            },
            {
                "request_id": "458255a1-3cec-4d25-8372-d0160d01d0e5",
                "data": "mafdb_29c4ddd140d117364cadffd440f0642c27bbc2412f4567e0cb32891cc3ef36a1.json"
            },
            {
                "request_id": "fb87c4e0-43ac-4582-b62a-3068a96ff711",
                "data": "mafdb_e61287967464938dd8658e2b6f8063c95a2a8288b950145c07d8cd279f06fe96.json"
            },
            {
                "request_id": "c59e179c-4c02-43b4-ad36-92efe19e25fe",
                "data": "mafdb_f15d6d133941e8137799af5c1c04fc577dd74e96149a2ccd80e4f571114f20e3.json"
            },
            {
                "request_id": "b03fede7-377b-4edd-bd06-d004503b3f79",
                "data": "mafdb_f6df04e8133221cbf519260251139ebd37c34febe492851dd4458992bca83c94.json"
            },
            {
                "request_id": "d5651935-20ad-49cd-9ca2-94d7008b3fc4",
                "data": "mafdb_5622c4af29c03a55db15361b96ebd57532e3d5deb3791cbd1444627fe1ca62ba.json"
            },
            {
                "request_id": "a17d14e4-9877-41f5-ae94-12f2932d45ad",
                "data": "mafdb_8fcd7595555ece58e0a06c2001637a9999683df07ff0bb320faaf120f0012491.json"
            },
            {
                "request_id": "640121e5-d75c-47bf-bff1-146baa4f93e7",
                "data": "mafdb_c47f40aaed70b274856370b8e6e48399beb4c8971c66ddd8be8d566d440a78a7.json"
            },
            {
                "request_id": "aaf6ab67-24e4-4550-89a1-565499c5cbe1",
                "data": "mafdb_bf6614cd56f098c5b75f97757054caf7ad0887c879d871d45b52d85ed0fd52d3.json"
            },
            {
                "request_id": "4fb12031-445e-4bbf-9430-c12476474a96",
                "data": "mafdb_fc2a84852f95eebd03a586abcf5a76c64db1efd965d2c472f2b8a03ed0c40edf.json"
            },
            {
                "request_id": "5696d07f-84a8-45fa-9d20-8a18c9213db1",
                "data": "mafdb_9b5e9882beb1fdd84eccf8fba19a31cf4a219df13f5ba94f1e8edd8742692a77.json"
            },
            {
                "request_id": "51c4c847-0f2c-4ef7-9940-71fbb4b05291",
                "data": "mafdb_028a779bdcb28d0db67ae99e8c383a2e5e0fd59fada6888e043db6f251521c76.json"
            },
            {
                "request_id": "de6281a2-7be0-449f-a039-dbaf0ca727eb",
                "data": "mafdb_a1bfbcddbd0327f872ff3e6b2d5dcbed9e804641918b58e4b469cf077329c2cd.json"
            },
            {
                "request_id": "be7322ca-ceb1-4227-b402-3f9d1f50c640",
                "data": "mafdb_c6f9bdcc9cf095b4cc92100a5d45f27a59abff72b82bc6fdea5fb67186885422.json"
            },
            {
                "request_id": "a2678edf-397f-4bfc-b96b-dee4bd89ce54",
                "data": "mafdb_076c9c757bf558a92d6744f8a09864a7bc11e5da777c7ae15a8572da59fdf706.json"
            },
            {
                "request_id": "649c2203-92ec-4edd-acaa-08d56a0e67ee",
                "data": "mafdb_c8628e7d7833590863c05945da0a15b09c0de52179e14bd524127f896a661506.json"
            },
            {
                "request_id": "613a0f8c-538e-481a-9399-d92be8fa509a",
                "data": "mafdb_af818f20f62fe0eeda8042dfb7efb70bbde191b72d033f6a645874911e2ac0ea.json"
            },
            {
                "request_id": "b050e327-7b3d-4c65-aa51-7431740b5a00",
                "data": "mafdb_d66a6c0e6284ab938bb396e2a94b21536e089891dd8678d3e232409e85974bf4.json"
            },
            {
                "request_id": "7ca0f2dc-c57f-46cb-8f37-426d2d9de9a8",
                "data": "mafdb_2cd07b4754913f8c45ff5e321c894937faa1dcee4409f0a9352ab164f3ab8dc2.json"
            },
            {
                "request_id": "ae32a1ef-2e8c-41f8-b8fe-9aafac26dde9",
                "data": "mafdb_42c39b281fccc83198017a319f363d9a14901ad1e7f2e87df206a5e5a893b775.json"
            },
            {
                "request_id": "60b825d9-7e24-4227-a794-72d87c56be15",
                "data": "mafdb_a2383066d212f15eacb4f5bfdf2ae197f1193622d791c3ccdfb8941fef8a2d4d.json"
            },
            {
                "request_id": "657150f9-4a27-4ee5-a9bc-aa52ba88b1f3",
                "data": "mafdb_6febe45619a64f41534b7849821df9e5f2a16cc6502a1d862c57cbd0c8b5d2df.json"
            },
            {
                "request_id": "14490d89-8696-4719-b3dc-e6005e6e2284",
                "data": "mafdb_5973609f30a5418d722dad186d12ca55876737215f0dc764dd048c27e245ccae.json"
            },
            {
                "request_id": "c2d904a3-435a-4e24-baee-f9625f9d99a6",
                "data": "mafdb_cb1762516f3107ce66e5f7512bdc20b07421fea478ab573ef564ba505b515612.json"
            },
            {
                "request_id": "dd01a148-dc64-4eda-b4e7-e193c6dafdf9",
                "data": "mafdb_d9174a4cf95376c6512c54a52da7d2f8c6f98dce795f8abb1e0b4736582eb76f.json"
            },
            {
                "request_id": "a3308ffe-2b23-4981-afe4-b12bf3601f74",
                "data": "mafdb_43869745aab3d63dfa68e4f287f1921924af17cf1395c9b35aca9cdc036d2b6a.json"
            },
            {
                "request_id": "8d512f77-3aa7-489b-8686-c6e32d35af81",
                "data": "mafdb_3c4715263643d510615654aef8ed8da557fffe96cf62eb913d276dfba2a90a55.json"
            },
            {
                "request_id": "95e3c6e4-b75e-4c2f-9d46-caf0435ae8fb",
                "data": "mafdb_1bc211752a94b2c578560693e27c96c128aefdf6439e0fc20a27028f333f2ca9.json"
            },
            {
                "request_id": "9048709b-8b32-4825-9ca3-0fb0a61cf3ad",
                "data": "mafdb_e1c1a3efbbe62c2a7b832722eea7a97c4c6a0584661d34d7903dfb1cb8550001.json"
            },
            {
                "request_id": "f65127b7-cb31-4216-8d22-587d9fab506e",
                "data": "mafdb_8d0251a64e765db63487e462f331f4afb2749626a0d1c4085bb8731ac3a5052b.json"
            },
            {
                "request_id": "45a5696f-9cd4-4003-98bd-025fb091aa91",
                "data": "mafdb_28ecc214cac63003cf7b528e48a95d9d281836f8056ca07c24592da99ada06e7.json"
            },
            {
                "request_id": "a53f5dea-fd11-4146-bd0a-993ced45a9ee",
                "data": "mafdb_e97fc06a644ed444f29205f62ad0887de8a84fba55d54a0ec90cd5febed725fd.json"
            },
            {
                "request_id": "ab5cd896-02a3-4439-85ca-811cde1597ca",
                "data": "mafdb_4555f69ce2c58254e8c25f01438d2c0763c3570e1c0d44ad7c518af8cc48fab3.json"
            },
            {
                "request_id": "3b7c1e67-7490-450d-8383-e29820378346",
                "data": "mafdb_fbc430092db6f27c57652a6d98f83f73df54adfe63f16dd4d3fda5ea19589601.json"
            },
            {
                "request_id": "0301f819-73e3-405d-ba33-30803e670c7a",
                "data": "mafdb_617f38c032965f822e4bfe80c4e2684669e23988975f7360111f1b2064da8be6.json"
            },
            {
                "request_id": "d9f07d49-4502-43ea-8a6e-bcc7b65970e8",
                "data": "mafdb_a1eedc391380a5657a304c22e8abeffea9d6dd787d36b21281414b4dc8af963a.json"
            },
            {
                "request_id": "b71798bc-22ea-48c1-9330-573cf2c9748f",
                "data": "mafdb_b37ce2a791ecfe787b7d2e61814968329db2169d06e3e6d0a2ffb4bdcf2dc2d6.json"
            },
            {
                "request_id": "53c915d6-abf8-4b72-a43c-1ff9f43de62b",
                "data": "mafdb_35ede6722fe824035d75d0534b754dd4b23ee9330ec089bb54db2128fededd5c.json"
            },
            {
                "request_id": "a6c9b25a-e1c7-4853-8b5b-adf4e2249b0a",
                "data": "mafdb_b68185c70cd2b2f6851e125ebe967c03331e2c7bb142d1bd978e8e475fd3780a.json"
            },
            {
                "request_id": "1ea255f5-d443-4cfe-aacc-cca644537a1d",
                "data": "mafdb_f918c820d318d5721f6a01c5e5f1bcf93d25c754add42dfe159109e02e35ab0a.json"
            }
        ],
        "final_mafdb_file": [
            {
                "request_id": "4a605210-b38b-4e08-98bd-6a06ff318814",
                "data": "mafdb_9686146ef12cbcadc2c152f32cd362e3a43d2843ac87454cb6ee23238b632061.json"
            }
        ]
    },
    "workflow_steps": [
        {
            "activity": "tree_constructor",
            "provider": "aws_lambda",
            "memory": 256,
            "strategy": "for_each_input",
            "data_params": {
                "input_files_path": "resources/data/full_dataset",
                "input_files_list": [
                    "ORTHOMCL1147",
                    "ORTHOMCL1092",
                    "ORTHOMCL1833",
                    "ORTHOMCL1311",
                    "ORTHOMCL1125",
                    "ORTHOMCL746",
                    "ORTHOMCL974",
                    "ORTHOMCL1940",
                    "ORTHOMCL320",
                    "ORTHOMCL964",
                    "ORTHOMCL763",
                    "ORTHOMCL1",
                    "ORTHOMCL1021",
                    "ORTHOMCL1352",
                    "ORTHOMCL1042",
                    "ORTHOMCL1136",
                    "ORTHOMCL1305",
                    "ORTHOMCL1005",
                    "ORTHOMCL617",
                    "ORTHOMCL1410",
                    "ORTHOMCL371",
                    "ORTHOMCL1958",
                    "ORTHOMCL1126",
                    "ORTHOMCL965",
                    "ORTHOMCL1166",
                    "ORTHOMCL510",
                    "ORTHOMCL875",
                    "ORTHOMCL256_2",
                    "ORTHOMCL854",
                    "ORTHOMCL1033",
                    "ORTHOMCL885",
                    "ORTHOMCL1408",
                    "ORTHOMCL1619",
                    "ORTHOMCL884",
                    "ORTHOMCL2001",
                    "ORTHOMCL744",
                    "ORTHOMCL1363",
                    "ORTHOMCL1984",
                    "ORTHOMCL1087",
                    "ORTHOMCL830",
                    "ORTHOMCL721",
                    "ORTHOMCL1034",
                    "ORTHOMCL1916",
                    "ORTHOMCL938",
                    "ORTHOMCL652"
                ],
                "param_in": "input_files",
                "param_out": "tree_files"
            },
            "active": true
        },
        {
            "activity": "subtree_constructor",
            "provider": "aws_lambda",
            "memory": 256,
            "strategy": "for_each_input",
            "data_params": {
                "param_in": "tree_files",
                "param_out": "subtree_files"
            },
            "active": true
        },
        {
            "activity": "maf_database_creator",
            "provider": "aws_lambda",
            "memory": 256,
            "strategy": "for_each_input",
            "data_params": {
                "param_in": "subtree_files",
                "param_out": "intermediate_mafdb_files"
            },
            "active": true
        },
        {
            "activity": "maf_database_aggregator",
            "provider": "aws_lambda",
            "memory": 256,
            "strategy": "for_all_inputs",
            "data_params": {
                "param_in": "intermediate_mafdb_files",
                "param_out": "final_mafdb_file"
            },
            "active": true
        }
    ],
    "provider_info": [
        {
            "provider_name": "AWS Lambda",
            "provider_tag": "aws_lambda",
            "configurations": [
                {
                    "timeout": 30,
                    "memory_mb": 128,
                    "cpu": 1,
                    "storage_mb": 512
                },
                {
                    "timeout": 45,
                    "memory_mb": 256,
                    "cpu": 1,
                    "storage_mb": 512
                },
                {
                    "timeout": 300,
                    "memory_mb": 512,
                    "cpu": 1,
                    "storage_mb": 512
                },
                {
                    "timeout": 300,
                    "memory_mb": 1024,
                    "cpu": 1,
                    "storage_mb": 512
                },
                {
                    "timeout": 300,
                    "memory_mb": 2048,
                    "cpu": 1,
                    "storage_mb": 512
                }
            ]
        },
        {
            "provider_name": "AWS EC2",
            "provider_tag": "aws_ec2",
            "configurations": [
                {
                    "timeout": 0,
                    "memory_mb": 1024,
                    "cpu": 1,
                    "storage_mb": 8192
                }
            ]
        },
        {
            "provider_name": "Local",
            "provider_tag": "local",
            "configurations": []
        }
    ],
    "workflow_info": {
        "workflow_name": "AWS Lambda Evaluation",
        "workflow_description": "Performance Evaluation of Lambda Functions in AWS",
        "activities": [
            {
                "activity_name": "tree_constructor",
                "activity_description": "Constructing Phylogenetic Trees from Protein Sequences"
            },
            {
                "activity_name": "subtree_constructor",
                "activity_description": "Generating Subtrees from Main Trees"
            },
            {
                "activity_name": "maf_database_creator",
                "activity_description": "Creating MAF Databases from Subtrees (Subtree Pair Frequency Matrix)"
            },
            {
                "activity_name": "maf_database_aggregator",
                "activity_description": "Aggregating MAF Databases"
            }
        ]
    },
    "statistics_info": {
        "default_separator": "\t",
        "default_statistics": {
            "START": [
                {
                    "searchKey": "RequestId",
                    "fieldName": "request_id",
                    "dataType": "string",
                    "separator": " "
                },
                {
                    "searchKey": "Version",
                    "fieldName": "version",
                    "dataType": "string"
                }
            ],
            "END": [
                {
                    "searchKey": "RequestId",
                    "fieldName": "request_id",
                    "dataType": "string"
                }
            ],
            "REPORT": [
                {
                    "searchKey": "RequestId",
                    "fieldName": "request_id",
                    "dataType": "string"
                },
                {
                    "searchKey": "Duration",
                    "fieldName": "duration",
                    "dataType": "float"
                },
                {
                    "searchKey": "Billed Duration",
                    "fieldName": "billed_duration",
                    "dataType": "float"
                },
                {
                    "searchKey": "Memory Size",
                    "fieldName": "memory_size",
                    "dataType": "integer"
                },
                {
                    "searchKey": "Max Memory Used",
                    "fieldName": "max_memory_used",
                    "dataType": "integer"
                },
                {
                    "searchKey": "Init Duration",
                    "fieldName": "init_duration",
                    "dataType": "float"
                }
            ],
            "FILE_TRANSFER": [
                {
                    "searchKey": "RequestId",
                    "fieldName": "request_id",
                    "dataType": "string"
                },
                {
                    "searchKey": "FileName",
                    "fieldName": "file_name",
                    "dataType": "string"
                },
                {
                    "searchKey": "Bucket",
                    "fieldName": "file_bucket",
                    "dataType": "string"
                },
                {
                    "searchKey": "FilePath",
                    "fieldName": "file_path",
                    "dataType": "string"
                },
                {
                    "searchKey": "FileSize",
                    "fieldName": "file_size",
                    "dataType": "integer"
                },
                {
                    "searchKey": "TransferType",
                    "fieldName": "transfer_type",
                    "dataType": "string"
                },
                {
                    "searchKey": "TransferDuration",
                    "fieldName": "transfer_duration",
                    "dataType": "float"
                }
            ],
            "CONSUMED_FILES_INFO": [
                {
                    "searchKey": "RequestId",
                    "fieldName": "request_id",
                    "dataType": "string"
                },
                {
                    "searchKey": "FilesCount",
                    "fieldName": "consumed_files_count",
                    "dataType": "integer"
                },
                {
                    "searchKey": "FilesSize",
                    "fieldName": "consumed_files_size",
                    "dataType": "integer"
                },
                {
                    "searchKey": "TransferDuration",
                    "fieldName": "consumed_files_transfer_duration",
                    "dataType": "float"
                }
            ],
            "PRODUCED_FILES_INFO": [
                {
                    "searchKey": "RequestId",
                    "fieldName": "request_id",
                    "dataType": "string"
                },
                {
                    "searchKey": "FilesCount",
                    "fieldName": "produced_files_count",
                    "dataType": "integer"
                },
                {
                    "searchKey": "FilesSize",
                    "fieldName": "produced_files_size",
                    "dataType": "integer"
                },
                {
                    "searchKey": "TransferDuration",
                    "fieldName": "produced_files_transfer_duration",
                    "dataType": "float"
                }
            ]
        },
        "custom_statistics": {
            "TREE_CONSTRUCTOR": [
                {
                    "searchKey": "RequestId",
                    "fieldName": "request_id",
                    "dataType": "string"
                },
                {
                    "searchKey": "Duration",
                    "fieldName": "tree_duration",
                    "dataType": "float",
                    "description": "Execution time of the tree construction activity"
                }
            ],
            "SUBTREE_CONSTRUCTOR": [
                {
                    "searchKey": "RequestId",
                    "fieldName": "request_id",
                    "dataType": "string"
                },
                {
                    "searchKey": "Duration",
                    "fieldName": "subtree_duration",
                    "dataType": "float",
                    "description": "Execution time of the subtree creation activity"
                }
            ],
            "MAF_DATABASE_CREATOR": [
                {
                    "searchKey": "RequestId",
                    "fieldName": "request_id",
                    "dataType": "string"
                },
                {
                    "searchKey": "InputSubtrees",
                    "fieldName": "input_subtrees",
                    "dataType": "string",
                    "description": "Subtrees used as input for the MAF database creation activity"
                },
                {
                    "searchKey": "Duration",
                    "fieldName": "maf_db_creator_duration",
                    "dataType": "float",
                    "description": "Execution time of the MAF database creation activity"
                }
            ],
            "MAF_DATABASE_AGGREGATOR": [
                {
                    "searchKey": "RequestId",
                    "fieldName": "request_id",
                    "dataType": "string"
                },
                {
                    "searchKey": "MaxMaf",
                    "fieldName": "max_maf",
                    "dataType": "integer",
                    "description": "Max MAF value found during input file processing"
                },
                {
                    "searchKey": "MafDatabase",
                    "fieldName": "maf_database",
                    "dataType": "string",
                    "description": "Value of the \"maf_database\" dictionary obtained at the end of the activity"
                },
                {
                    "searchKey": "Duration",
                    "fieldName": "maf_db_aggregator_duration",
                    "dataType": "float",
                    "description": "Execution time of the MAF database aggregation activity"
                }
            ]
        }
    },
    "env_properties": {
        "denethor": {
            "log.path": "resources/logs/[provider_tag]",
            "log.file": "log_[execution_tag]_[activity_name].log",
            "log.metadata_file": "[execution_tag]_[n_files]_files__[memory]_memory.json"
        },
        "bucket": {
            "name": "denethor",
            "key.input_files": "data/full_dataset",
            "key.tree_constructor": "tree",
            "key.subtree_constructor": "subtree",
            "key.maf_database_creator": "mafdb",
            "key.maf_database_aggregator": "mafdb"
        },
        "aws_lambda": {
            "data_format": "nexus",
            "path.input_files": "/tmp/input",
            "path.tmp": "/tmp",
            "path.tree_constructor": "/tmp/tree",
            "path.subtree_constructor": "/tmp/subtree",
            "path.maf_database_creator": "/tmp/mafdb",
            "path.maf_database_aggregator": "/tmp/mafdb",
            "path.clustalw": "/opt/python/clustalw-2.1-linux",
            "log.output_type": "stdout"
        },
        "aws_ec2": {
            "instance_id": "i-0f2f2ec6dd1e6a455",
            "data_format": "nexus",
            "path.src": "src/lambda",
            "target_method": "handler",
            "path.input_files": "resources/data/full_dataset",
            "path.tmp": ".tmp",
            "path.tree_constructor": ".tmp/tree",
            "path.subtree_constructor": ".tmp/subtree",
            "path.maf_database_creator": ".tmp/mafdb",
            "path.maf_database_aggregator": ".tmp/mafdb",
            "path.clustalw": "resources/libs/clustalw-2.1-linux",
            "log.output_type": "file"
        },
        "local": {
            "data_format": "nexus",
            "path.src": "src/lambda",
            "target_method": "handler",
            "path.input_files": "resources/data/full_dataset",
            "path.tmp": ".tmp",
            "path.tree_constructor": ".tmp/tree",
            "path.subtree_constructor": ".tmp/subtree",
            "path.maf_database_creator": ".tmp/mafdb",
            "path.maf_database_aggregator": ".tmp/mafdb",
            "path.clustalw": "resources/libs/clustalw-2.1-linux",
            "log.output_type": "stdout_and_file"
        }
    }
}